wordreduce/__init__.py
wordreduce/natural_text_tokenizer.py
wordreduce/util.py
wordreduce/wordreduce.py
wordreduce-0.0.1.dist-info/LICENSE
wordreduce-0.0.1.dist-info/METADATA
wordreduce-0.0.1.dist-info/WHEEL
wordreduce-0.0.1.dist-info/top_level.txt
wordreduce-0.0.1.dist-info/RECORD
