Metadata-Version: 2.1
Name: wordreduce
Version: 0.0.1
Author-email: Jordi Carrera Ventura <jordi.carrera.ventura@gmail.com>
Project-URL: GitHub repository page, https://github.com/JordiCarreraVentura/wordreduce
Classifier: Programming Language :: Python :: 3
Classifier: Operating System :: OS Independent
Requires-Python: >=3.11
License-File: LICENSE
Requires-Dist: build
Requires-Dist: numpy==2.1.3
Requires-Dist: pandas==2.2.3
Requires-Dist: pytest==8.3.4
Requires-Dist: scikit-learn==1.5.2
Requires-Dist: twine
Requires-Dist: Unidecode==1.3.8
